{
  "name": "Basic Web3 - Verifier Example",
  "version": 1,
  "description": "Basic Web3 journey with address, ETH, ERC20, NFT on mainnet and polygon",
  "website": "https://www.ethereum.org/",
  "twitter": "fjun99",
  "tasks": [
    {
      "name": "Have a wallet address",
      "description": "You need a wallet address to enter Web3 universe.",
      "points": 100,
      "verifier": {
        "id": "active-address"
      }
    },
    {
      "name": "Have ETH in wallet",
      "description": "Own some ETH. Using verifier `has-ETH`",
      "points": 400,
      "verifier": {
        "id": "has-ETH",
        "params": {
          "amount": 0.01
        }
      }
    },
    {
      "name": "Have MATIC in polygon wallet",
      "description": "Own some MATIC on polygon. Using verifier `has-ETH`",
      "points": 400,
      "verifier": {
        "id": "has-ETH",
        "chainId": 137,
        "params": {
          "amount": 0.1
        }
      }
    },
    {
      "name": "ERC20: has 10+ ENS Token",
      "description": "Own 10+ ENS ERC20 Token. Using verifier `has-token-ERC20`",
      "points": 400,
      "verifier": {
        "id": "has-token-ERC20",
        "params": {
          "tokenAddress": "0xC18360217D8F7Ab5e7c516566761Ea12Ce7F9D72",
          "amount": 10
        }
      }
    },
    {
      "name": "ERC20: has WETH on polygon",
      "description": "Own some WETH (Wrapped ETH, ERC20 Token) on polygon. Using verifier `has-token-ERC20`",
      "points": 400,
      "verifier": {
        "id": "has-token-ERC20",
        "chainId": 137,
        "params": {
          "tokenAddress": "0x7ceB23fD6bC0adD59E62ac25578270cFf1b9f619"
        }
      }
    },
    {
      "name": "Own an ERC721 NFT",
      "description": "Own an ENS NFT(ERC721). Using verifier `has-nft-ERC721`",
      "points": 400,
      "verifier": {
        "id": "has-nft-ERC721",
        "params": {
          "tokenAddress": "0x57f1887a8bf19b14fc0df6fd9b2acc9af147ea85"
        }
      }
    },
    {
      "name": "Own an ERC721 NFT on polygon",
      "description": "Own an NFT on Polygon network. Using verifier `has-token-ERC721`",
      "points": 400,
      "verifier": {
        "id": "has-nft-ERC721",
        "chainId": 137,
        "params": {
          "tokenAddress": "0x7eb476Cd0fE5578106A01DC2f2E392895C6BC0A5"
        }
      }
    }
  ]
}